gramscript/__init__.py
gramscript/__version__.py
gramscript/api.py
gramscript/delegate.py
gramscript/exception.py
gramscript/filtering.py
gramscript/hack.py
gramscript/helper.py
gramscript/loop.py
gramscript/namedtuple.py
gramscript/routing.py
gramscript/text.py
gramscript/aio/__init__.py
gramscript/aio/api.py
gramscript/aio/delegate.py
gramscript/aio/hack.py
gramscript/aio/helper.py
gramscript/aio/loop.py
gramscript/aio/routing.py
gramscript-1.0.2.dist-info/LICENSE
gramscript-1.0.2.dist-info/METADATA
gramscript-1.0.2.dist-info/WHEEL
gramscript-1.0.2.dist-info/top_level.txt
gramscript-1.0.2.dist-info/RECORD
