Metadata-Version: 2.1
Name: gramscript
Version: 1.0.2
Summary: Powerful, MTProto API framework in Python for users and bots
Home-page: https://github.com/gramscript/gramscript
Author: kalanakt
Author-email: kalanakt <e19198@eng.pdn.ac.lk>
License: MIT License        
Project-URL: Homepage, https://github.com/gramscript/gramscript.py
Project-URL: Bug Tracker, https://github.com/gramscript/gramscript.py/issues
Keywords: telegram bot api python wrapper
Classifier: Programming Language :: Python :: 3
Classifier: License :: OSI Approved :: MIT License
Classifier: Operating System :: OS Independent
Requires-Python: >=3.7
License-File: LICENSE
Requires-Dist: urllib3 (>=1.9.1)
Requires-Dist: aiohttp (>=3.0.0)
